uksic/__init__.py
uksic/etl/__init__.py
uksic/etl/app.py
uksic/etl/download.py
uksic/etl/extract.py
uksic-0.0.1.dist-info/METADATA
uksic-0.0.1.dist-info/WHEEL
uksic-0.0.1.dist-info/licenses/LICENSE
uksic-0.0.1.dist-info/RECORD
