Metadata-Version: 2.4
Name: uksic
Version: 0.0.1
Summary: UK Standard Industrial Classification (SIC)
Project-URL: Homepage, https://github.com/acculayer/uksic
Project-URL: Issues, https://github.com/acculayer/uksic/issues
Author-email: Voquis Limited <opensource@voquis.com>
License-File: LICENSE
Classifier: License :: OSI Approved :: MIT License
Classifier: Operating System :: OS Independent
Classifier: Programming Language :: Python :: 3
Requires-Python: >=3.11
Requires-Dist: httpx
Requires-Dist: openpyxl
Requires-Dist: pandas
Provides-Extra: dev
Requires-Dist: build; extra == 'dev'
Requires-Dist: pylint; extra == 'dev'
Requires-Dist: pytest; extra == 'dev'
Requires-Dist: pytest-cov; extra == 'dev'
Requires-Dist: pytest-httpx; extra == 'dev'
Requires-Dist: ruff; extra == 'dev'
Requires-Dist: twine; extra == 'dev'
